jk_typing/__init__.py
jk_typing/checkFunctionSignature.py
jk_typing/checking/AbstractCTNode.py
jk_typing/checking/CTAlwaysTrue.py
jk_typing/checking/CTIsCallable.py
jk_typing/checking/CTIsDict.py
jk_typing/checking/CTIsNone.py
jk_typing/checking/CTIsSequence.py
jk_typing/checking/CTIsType.py
jk_typing/checking/CTIsType.py.sav.OLD
jk_typing/checking/CTIsType__CheckItems_AllTheSameType.py
jk_typing/checking/CTIsType__CheckItems_ExactTypeSequence.py
jk_typing/checking/CTIsType__Single_NewType.py
jk_typing/checking/CTIsType__Single_None.py
jk_typing/checking/CTIsType__Union.py
jk_typing/checking/CheckTypeCompiler.py
jk_typing/checking/__init__.py
jk_typing-0.2024.1.3.dist-info/WHEEL
jk_typing-0.2024.1.3.dist-info/METADATA
jk_typing-0.2024.1.3.dist-info/RECORD
