Metadata-Version: 2.1
Name: jk_typing
Version: 0.2024.1.3
Summary: This module provides capabilities for type checking function arguments. (NOTE: A full type check with this module is not possible, since this is fundamentally not possible due to limitiations of Python itself.)
Keywords: typing,type-checking
Author-email: Jürgen Knauth <pubsrc@binary-overflow.de>
Maintainer-email: Jürgen Knauth <pubsrc@binary-overflow.de>
Requires-Python: >=3.8
Classifier: Development Status :: 5 - Production/Stable
Classifier: License :: OSI Approved :: Apache Software License
Classifier: Programming Language :: Python :: 3
